freshrss_api/__init__.py
freshrss_api/freshrss_api.py
freshrss_api/utils/__init__.py
freshrss_api/utils/errors.py
freshrss_api/utils/items.py
freshrss_api-2.0.5.dist-info/licenses/LICENSE
freshrss_api-2.0.5.dist-info/METADATA
freshrss_api-2.0.5.dist-info/WHEEL
freshrss_api-2.0.5.dist-info/top_level.txt
freshrss_api-2.0.5.dist-info/RECORD
