Metadata-Version: 2.4
Name: freshrss_api
Version: 2.0.5
Summary: Easy to use python api to get data from FreshRSS
Home-page: https://github.com/thiswillbeyourgithub/freshrss_python_api/
Keywords: rss,freshrss,python,api,feeds
Classifier: Programming Language :: Python :: 3
Classifier: Operating System :: OS Independent
Requires-Python: >=3.9
License-File: LICENSE
Requires-Dist: requests>=2.32.3
Requires-Dist: beautifulsoup4>=4.13.4
Dynamic: classifier
Dynamic: description
Dynamic: description-content-type
Dynamic: home-page
Dynamic: keywords
Dynamic: license-file
Dynamic: requires-dist
Dynamic: requires-python
Dynamic: summary
